pystrand/__init__.py
pystrand/fitnessfunctions.py
pystrand/genotypes.py
pystrand/loggers/__init__.py
pystrand/loggers/base.py
pystrand/loggers/csv_logger.py
pystrand/loggers/details.py
pystrand/models/__init__.py
pystrand/models/base_models.py
pystrand/models/polymodels.py
pystrand/operators/__init__.py
pystrand/operators/mutations.py
pystrand/operators/selections.py
pystrand/optimizers.py
pystrand/populations.py
pystrand-0.1.1.dist-info/LICENSE
pystrand-0.1.1.dist-info/WHEEL
pystrand-0.1.1.dist-info/METADATA
pystrand-0.1.1.dist-info/RECORD
