Metadata-Version: 2.1
Name: pystrand
Version: 0.1.1
Summary: Python genetic algorithm package
License: BSD 3-Clause License
Author: Jiri Podivin
Author-email: jpodivin@gmail.com
Requires-Python: >=3.8,<4.0
Classifier: License :: Other/Proprietary License
Classifier: Programming Language :: Python :: 3
Classifier: Programming Language :: Python :: 3.8
Classifier: Programming Language :: Python :: 3.9
Classifier: Programming Language :: Python :: 3.10
Requires-Dist: numpy (>=1.18.5,<2.0.0)
Requires-Dist: pandas (>=1.2.0,<2.0.0)
